wgcf.py
wgcf-0.1.0.dist-info/WHEEL
wgcf-0.1.0.dist-info/METADATA
wgcf-0.1.0.dist-info/RECORD
